marsgpt/__init__.py
marsgpt/gpt2.py
marsgpt/util.py
marsgpt-0.1.6.dist-info/LICENSE
marsgpt-0.1.6.dist-info/METADATA
marsgpt-0.1.6.dist-info/WHEEL
marsgpt-0.1.6.dist-info/top_level.txt
marsgpt-0.1.6.dist-info/RECORD
