Metadata-Version: 2.1
Name: marsgpt
Version: 0.1.6
Summary: Mars ChatGPT API Lib
Home-page: UNKNOWN
Author-email: yanjingang@mail.com
License: UNKNOWN
Platform: UNKNOWN
Requires-Dist: asyncio
Requires-Dist: httpx[socks]
Requires-Dist: OpenAIAuth (==0.2.0)
Requires-Dist: tiktoken
Requires-Dist: requests
Requires-Dist: tornado
